thermal/__init__.py
thermal/sample/__init__.py
thermal/sample/_interface.py
thermal/sample/generic.py
thermal/sample/gmm.py
thermal/sample/hist.py
thermal/sample/kde.py
thermal/stats/__init__.py
thermal/stats/samples_tests.py
thermal/thermal.py
thermal-0.6.3.dist-info/entry_points.txt
thermal-0.6.3.dist-info/LICENSE
thermal-0.6.3.dist-info/WHEEL
thermal-0.6.3.dist-info/METADATA
thermal-0.6.3.dist-info/RECORD
