Metadata-Version: 2.1
Name: thermal
Version: 0.6.3
Summary: Surrogate times eries generation.
Home-page: https://github.com/sitmo/thermal
License: MIT
Author: Thijs van den Berg
Author-email: thijs@sitmo.com
Requires-Python: >=3.8.0,<3.11
Classifier: Development Status :: 2 - Pre-Alpha
Classifier: Intended Audience :: Developers
Classifier: License :: OSI Approved :: MIT License
Classifier: Natural Language :: English
Classifier: Programming Language :: Python :: 3
Classifier: Programming Language :: Python :: 3.10
Classifier: Programming Language :: Python :: 3.8
Classifier: Programming Language :: Python :: 3.9
Provides-Extra: dev
Provides-Extra: docs
Provides-Extra: test
Requires-Dist: Sphinx (>=4.5.0,<5.0.0); extra == "docs"
Requires-Dist: black (>=22.3.0,<23.0.0); extra == "test"
Requires-Dist: bump2version (>=1.0.1,<2.0.0); extra == "dev"
Requires-Dist: click (==8.0.4)
Requires-Dist: flake8 (>=3.9.2,<4.0.0); extra == "test"
Requires-Dist: flake8-docstrings (>=1.6.0,<2.0.0); extra == "test"
Requires-Dist: isort (>=5.8.0,<6.0.0); extra == "test"
Requires-Dist: mypy (>=0.900,<0.901); extra == "test"
Requires-Dist: myst-parser (>=0.17.2,<0.18.0)
Requires-Dist: nbsphinx (>=0.8.8,<0.9.0); extra == "docs"
Requires-Dist: numpy (>=1.22.3,<2.0.0)
Requires-Dist: pip (>=20.3.1,<21.0.0); extra == "dev"
Requires-Dist: pre-commit (>=2.12.0,<3.0.0); extra == "dev"
Requires-Dist: pytest (>=6.2.4,<7.0.0); extra == "test"
Requires-Dist: pytest-cov (>=2.12.0,<3.0.0); extra == "test"
Requires-Dist: scipy (>=1.8.0,<2.0.0)
Requires-Dist: sklearn (>=0.0,<0.1)
Requires-Dist: sphinx-rtd-theme (>=1.0.0,<2.0.0); extra == "docs"
Requires-Dist: toml (>=0.10.2,<0.11.0); extra == "dev"
Requires-Dist: tox (>=3.20.1,<4.0.0); extra == "dev"
Requires-Dist: twine (>=3.3.0,<4.0.0); extra == "dev"
Requires-Dist: virtualenv (>=20.2.2,<21.0.0); extra == "dev"
